{
  "language": "ar",
  "title": "WaveSpeed AI - مولد الفراكتلات بالذكاء الاصطناعي",
  "meta": {
    "description": "قم بإنشاء صور فراكتل رائعة ومعقدة بلا حدود باستخدام الذكاء الاصطناعي. مثالي للفن الرقمي، ومشاريع التصميم، ورسومات الخلفية. مثالي للفنانين والمبدعين الذين يتطلعون لتعزيز أعمالهم بسهولة.",
    "keywords": "مولد فراكتل بالذكاء الاصطناعي، فن الفراكتل، مولد الفن الرقمي، فن مولد، أداة تصميم بالذكاء الاصطناعي، فراكتلات مخصصة، مولد خلفيات فنية، أدوات الذكاء الاصطناعي الإبداعية، فراكتلات WaveSpeed، صانع الصور الفنية، منشئ المحتوى المرئي"
  },
  "header": {
    "nav": [
      {
        "label": "الرئيسية",
        "items": [
          [
            "الرئيسية",
            "https://wavespeed.ai/"
          ]
        ]
      },
      {
        "label": "أدوات الذكاء الاصطناعي",
        "items": [
          [
            "أدوات الذكاء الاصطناعي",
            "#ai_tools"
          ]
        ]
      },
      {
        "label": "عرض",
        "items": [
          [
            "عرض",
            "https://wavespeed.ai/studio/ecommerce/showcase"
          ]
        ]
      }
    ],
    "tryText": "جرّبها الآن"
  },
  "hero": {
    "heading": "إنشاء فن الفراكتل",
    "subHeading": "أطلق الفراكتلات الرائعة في متناول يديك",
    "description": "قم بإنشاء تصاميم فراكتل مدهشة بسهولة باستخدام أداتنا المدعومة بالذكاء الاصطناعي. أنشئ أعمالًا فنية فريدة تبهر بها الجميع في لحظات. مثالي للفنانين والمصممين وأي شخص يتطلع لتعزيز محتوى مرئي.",
    "tryText": "جرّبها الآن",
    "videoUrl": "https://wavespeed.ai/studio/ecommerce/images/homePage/imageToVideo.mp4"
  },
  "compare": {
    "heading": "حل مولد الفراكتلات WaveSpeed AI",
    "left": {
      "heading": "التحديات التقليدية",
      "items": [
        "إنشاء الفراكتلات يتطلب معرفة معقدة بالبرمجة",
        "تعديلات يدوية تستغرق وقتًا",
        "خيارات محدودة للإبداع والتصميم",
        "نتائج أقل جودة من البرمجيات التقليدية",
        "تكاليف عالية للأدوات التوليدية الحالية"
      ]
    },
    "right": {
      "heading": "حل WaveSpeedAI",
      "items": [
        "إنشاء تصاميم فراكتل فريدة في ثوانٍ",
        "لا حاجة لمهارات برمجية - فقط بضع نقرات",
        "الذكاء الاصطناعي يعزز الإبداع مع تنوع لا حدود له",
        "نموذج دفع معقول حسب الاستخدام",
        "إنتاج فن عالي الجودة بسرعة وسهولة"
      ],
      "tryText": "جرّب"
    }
  },
  "howItWorks": {
    "heading": "كيف يعمل",
    "description": "إنشاء فراكتلات جذابة في 4 خطوات بسيطة",
    "steps": [
      {
        "number": "1",
        "title": "اختر المتغيرات الأساسية",
        "text": "اختر الإعدادات الأولية لتصميم الفراكتل الخاص بك",
        "color": "#3b82f6",
        "icon": "BlueStar"
      },
      {
        "number": "2",
        "title": "خصص تصميمك",
        "text": "عدل الألوان والأشكال والتعقيد حسب الرغبة",
        "color": "#a855f7",
        "icon": "PurpleCircle"
      },
      {
        "number": "3",
        "title": "عرض فراكتلك",
        "text": "شاهد عرضًا مباشرًا لإنشاء فراكتلك",
        "color": "#14b8a6",
        "icon": "GreenSquares"
      },
      {
        "number": "4",
        "title": "قم بتنزيل العمل الفني",
        "text": "احصل على صور فراكتل رائعة جاهزة للاستخدام",
        "color": "#fb923c",
        "icon": "OrangeHex"
      }
    ],
    "generateText": "إنشاء فراكتلك الأول →"
  },
  "endlessPossibilities": {
    "heading": "احتمالات لا حصر لها",
    "description": "إلهام لكل مسعى فني",
    "items": [
      "خلفيات فريدة للمواقع والعروض التقديمية",
      "طباعة فنية للمنتجات",
      "فن رقمي لمنشورات وسائل التواصل الاجتماعي",
      "أصول إبداعية لمحتوى الفيديو",
      "مكونات بصرية لتصميم الجرافيك",
      "أعمال فنية محسنة للمعارض",
      "أنماط مبتكرة لتصميم الأقمشة",
      "ورق حائط وزخارف مخصصة"
    ]
  },
  "successStories": {
    "heading": "قصص نجاح حقيقية",
    "description": "شاهد كيف يغير المبدعون فنهم باستخدام الذكاء الاصطناعي",
    "items": [
      {
        "tag": "فنان رقمي",
        "heading": "عمل فني فريد لمحفظة عبر الإنترنت",
        "before": {
          "label": "قبل",
          "text": "تصميمات أساسية"
        },
        "after": {
          "label": "بعد",
          "text": "فراكتلات نابضة ومعقدة"
        },
        "value": "150%",
        "key": "تحسين في التفاعل",
        "description": "ارتفعت رؤية محفظتي بشكل كبير بعد إضافة فراكتلات مولدة بالذكاء الاصطناعي. العملاء مندهشون من التصميمات الفريدة."
      },
      {
        "tag": "مصمم جرافيك",
        "heading": "أنماط مخصصة للعلامة التجارية",
        "before": {
          "label": "قبل",
          "text": "تصميمات متكررة"
        },
        "after": {
          "label": "بعد",
          "text": "رسوميات جذابة ومخصصة"
        },
        "value": "120%",
        "key": "زيادة في رضا العملاء",
        "description": "بادرتني الفراكتلات لإنشاء تصميمات بارزة تمثل بوضوح علامات تجارية لعملائي."
      }
    ]
  },
  "modelComparison": {
    "heading": "مقارنة نماذج الفراكتل",
    "description": "اختر إعدادات الفراكتل المناسبة لمشروعك",
    "items": [
      "نوع الفراكتل A: أنماط معقدة، تفاصيل غنية، جيل بطيء",
      "نوع الفراكتل B: أشكال بسيطة، جيل سريع، مثالي للخلفيات",
      "خيارات تخصيص لا حصر لها لكل مشروع",
      "تقديم في الوقت الفعلي لمعاينات فورية",
      "مخرجات عالية الدقة للاستخدام المهني"
    ]
  },
  "relatedAITools": {
    "heading": "أدوات الذكاء الاصطناعي ذات الصلة",
    "description": "استكشف المزيد من حلول الذكاء الاصطناعي الإبداعية المتقدمة"
  },
  "faq": {
    "heading": "الأسئلة المتكررة",
    "description": "كل ما تحتاج لمعرفته",
    "items": [
      {
        "question": "ما نوع تصميمات الفراكتل التي يمكنني إنشاؤها؟",
        "answer": "يمكنك إنشاء مجموعة واسعة من الفراكتلات، تتراوح من تصميمات بسيطة إلى أنماط معقدة. تتيح لك الأداة تخصيص الألوان والأشكال والتعقيد لاحتمالات لا حصر لها."
      },
      {
        "question": "هل أحتاج إلى أي مهارات فنية لاستخدام المولد؟",
        "answer": "لا! يبسط الذكاء الاصطناعي إنشاء الفراكتلات، مما يجعلها متاحة للجميع، بغض النظر عن خلفيتهم الفنية. فقط قم بضبط معلماتك واترك الذكاء الاصطناعي يتولى البقية."
      },
      {
        "question": "هل يمكنني استخدام الفراكتلات تجارياً؟",
        "answer": "نعم! جميع الفراكتلات التي يتم إنشاؤها عبر WaveSpeed تأتي مع حقوق تجارية كاملة، مما يسمح لك باستخدامها للتسويق أو المبيعات أو المشاريع الشخصية دون أي رسوم إضافية."
      },
      {
        "question": "كم من الوقت يمكنني إنشاء الفراكتلات؟",
        "answer": "يمكن إنشاء الفراكتلات في ثوانٍ، اعتمادًا على تعقيد تصميمك. معظم التصميمات جاهزة للتنزيل تقريبًا على الفور!"
      },
      {
        "question": "ما تنسيقات الملفات التي أستقبلها لفراكتلاتي؟",
        "answer": "يمكنك تنزيل الفراكتلات الخاصة بك بتنسيقات PNG وJPEG عالية الجودة، مثالية للاستخدام الرقمي والطباعة."
      },
      {
        "question": "هل هناك حد لعدد الفراكتلات التي يمكنني إنشاؤها؟",
        "answer": "لا توجد حدود! يمكنك إنشاء أي عدد تريده من الفراكتلات، مما يتيح لك حرية إبداعية كاملة."
      },
      {
        "question": "ماذا لو أردت إجراء تعديلات على فراكتل؟",
        "answer": "يمكنك بسهولة العودة لضبط المعلمات وتجديد الفراكتل للحصول على التصميم المثالي الذي تريده."
      },
      {
        "question": "هل هناك دعم متاح إذا واجهت مشاكل؟",
        "answer": "بالطبع! فريق الدعم لدينا متاح لمساعدتك في أي أسئلة أو مخاوف قد تطرأ أثناء استخدام المولد."
      }
    ]
  },
  "cta": {
    "heading": "هل أنت مستعد لإنشاء فراكتلك الأول؟",
    "description": "ابدأ مع رصيد مجاني - اختبر الإبداع بنفسك",
    "contactUsText": "اتصل بنا",
    "tryText": "جرّبها الآن →"
  },
  "footer": {
    "heading": "هل أنت مستعد لإنشاء فراكتلات رائعة؟",
    "description": "جرّب WaveSpeed AI الآن وعيش الابتكار بنفسك. لا حاجة للتسجيل.",
    "ctaText": "أنشئ فراكتلك الآن",
    "text": "© 2025 WaveSpeed AI. جميع الحقوق محفوظة."
  }
}